services_registry/__init__.py
services_registry/services_registry.py
services_registry-0.0.1.dist-info/LICENSE
services_registry-0.0.1.dist-info/METADATA
services_registry-0.0.1.dist-info/WHEEL
services_registry-0.0.1.dist-info/top_level.txt
services_registry-0.0.1.dist-info/RECORD
