Metadata-Version: 2.1
Name: services-registry
Version: 0.0.1
Summary: A registry for managing services in Python applications
Author-email: Yaroslav Grebnov <grebnov@gmail.com>
License: The MIT License (MIT)        
Project-URL: Homepage, https://github.com/ygrebnov/services-registry
Project-URL: Bug Tracker, https://github.com/ygrebnov/services-registry/issues
Classifier: Programming Language :: Python :: 3
Classifier: License :: OSI Approved :: MIT License
Classifier: Operating System :: OS Independent
Requires-Python: >=3.6
License-File: LICENSE
Provides-Extra: test
Requires-Dist: pytest ; extra == 'test'
